kunkupackage/__init__.py
kunkupackage/module1.py
kunkupackage/module2.py
kunkupackage/test.py
kunkupackage-0.0.1.dist-info/LICENSE.txt
kunkupackage-0.0.1.dist-info/METADATA
kunkupackage-0.0.1.dist-info/WHEEL
kunkupackage-0.0.1.dist-info/top_level.txt
kunkupackage-0.0.1.dist-info/RECORD
